{
  "info": {
    "version": {
      "content": "自动更新测试完成！\n关注永雏塔菲喵\n更新好丑",
      "time": "2022-07-22 04:39",
      "versionCode": "1",
      "version": "1.0.1",
      "path": "https://ly-xxx.github.io/ace_taffy_app_distribution/ace_taffy_1.0beta.apk"
    },
    "links": {
      "taffyHomePage": "https://space.bilibili.com/1265680561",
      "yeexHomePage": "https://space.bilibili.com/291386365",
      "staUrls": [
        "https://space.bilibili.com/1265680561",
        "https://vtbs.moe/detail/1265680561",
        "https://vup.darkflame.ga/ranking/month",
        "https://vup.darkflame.ga/ranking/day",
        "https://playboard.co/en/youtube-ranking/most-popular-v-tuber-channels-in-worldwide-daily"
      ],
      "staNames": [
        "taffy主页",
        "vtbs.moe",
        "VupLiveChatRecorder-月榜",
        "VupLiveChatRecorder-日榜",
        "playboard"
      ],
      "pltUrls": [
        "https://space.bilibili.com/1265680561/dynamic",
        "https://weibo.com/n/%E6%B0%B8%E9%9B%8F%E5%A1%94%E8%8F%B2",
        "https://v.douyin.com/2dDN4G5/",
        "https://shop249421460.m.taobao.com/",
        "https://www.youtube.com/channel/UC-WTKBWDsp0PFcGmmuO7svg",
        "https://twitter.com/AceTaffy812"
      ],
      "pltNames": [
        "bilibili",
        "微博",
        "抖音（短视频！看一支）",
        "淘宝（买！）",
        "youtube",
        "twitter"
      ],
      "bbsUrls": [
        "https://tieba.baidu.com/f?kw=%E6%B0%B8%E9%9B%8F%E5%A1%94%E8%8F%B2",
        "https://tieba.baidu.com/f?kw=%E5%8F%8D%E6%B0%B8%E9%9B%8F%E5%A1%94%E8%8F%B2",
        "https://tieba.baidu.com/f?kw=v",
        "https://www.bilibili.com/h5/channel/4429874",
        "https://www.bilibili.com/h5/channel/860",
        "https://tieba.baidu.com/f?kw=%E7%83%AD%E6%B0%B4%E5%99%A8"
      ],
      "bbsNames": [
        "永雏塔菲吧",
        "反永雏塔菲吧",
        "V吧",
        "bilibili虚拟up主话题",
        "bilibili日本话题",
        "热水器吧"
      ]
    }
  }
}